pyqt_svg_icon_pushbutton/__init__.py
pyqt_svg_icon_pushbutton/svgIconPushButton.py
pyqt_svg_icon_pushbutton-0.0.15.dist-info/LICENSE
pyqt_svg_icon_pushbutton-0.0.15.dist-info/METADATA
pyqt_svg_icon_pushbutton-0.0.15.dist-info/WHEEL
pyqt_svg_icon_pushbutton-0.0.15.dist-info/top_level.txt
pyqt_svg_icon_pushbutton-0.0.15.dist-info/RECORD
