Metadata-Version: 2.1
Name: pyqt-svg-icon-pushbutton
Version: 0.0.15
Summary: PyQt QPushButton which user can set svg icon (not a fake low quality svg icon)
Home-page: https://github.com/yjg30737/pyqt-svg-icon-pushbutton.git
Author: Jung Gyu Yoon
Author-email: yjg30737@gmail.com
License: MIT
Platform: UNKNOWN
License-File: LICENSE
Requires-Dist: PyQt5 (>=5.8)
Requires-Dist: absresgetter (>=0.0.1)
